pyslang.cpython-39-darwin.so
pyslang-9.1.0.dist-info/RECORD
pyslang-9.1.0.dist-info/WHEEL
pyslang-9.1.0.dist-info/METADATA
pyslang-9.1.0.dist-info/licenses/LICENSE
