Metadata-Version: 2.2
Name: pyslang
Version: 9.1.0
Summary: Python bindings for slang, a library for compiling SystemVerilog
Keywords: slang,verilog,systemverilog,parsing,compiler,eda
Author: Mike Popoloski
License: Copyright (c) 2015-2025 Michael Popoloski
Classifier: Development Status :: 5 - Production/Stable
Classifier: Intended Audience :: Developers
Classifier: License :: OSI Approved :: MIT License
Classifier: Operating System :: MacOS :: MacOS X
Classifier: Operating System :: Microsoft :: Windows
Classifier: Operating System :: POSIX :: Linux
Classifier: Operating System :: Unix
Classifier: Programming Language :: C++
Classifier: Programming Language :: Python :: 3
Classifier: Topic :: Scientific/Engineering :: Electronic Design Automation (EDA)
Classifier: Topic :: Software Development :: Compilers
Classifier: Topic :: Software Development :: Libraries :: Python Modules
Project-URL: Homepage, https://sv-lang.com/
Project-URL: Documentation, https://sv-lang.com/pyslang/
Project-URL: Repository, https://github.com/MikePopoloski/slang
Project-URL: Issues, https://github.com/MikePopoloski/slang/issues
Project-URL: Changelog, https://github.com/MikePopoloski/slang/blob/master/CHANGELOG.md
Provides-Extra: test
Requires-Dist: pytest; extra == "test"
